setup.py
timesketch_cli_client/__init__.py
timesketch_cli_client/cli.py
timesketch_cli_client/definitions.py
timesketch_cli_client/test_lib.py
timesketch_cli_client/version.py
timesketch_cli_client.egg-info/PKG-INFO
timesketch_cli_client.egg-info/SOURCES.txt
timesketch_cli_client.egg-info/dependency_links.txt
timesketch_cli_client.egg-info/entry_points.txt
timesketch_cli_client.egg-info/not-zip-safe
timesketch_cli_client.egg-info/requires.txt
timesketch_cli_client.egg-info/top_level.txt
timesketch_cli_client/commands/__init__.py
timesketch_cli_client/commands/analyze.py
timesketch_cli_client/commands/attribute.py
timesketch_cli_client/commands/config.py
timesketch_cli_client/commands/events.py
timesketch_cli_client/commands/events_test.py
timesketch_cli_client/commands/importer.py
timesketch_cli_client/commands/intelligence.py
timesketch_cli_client/commands/intelligence_test.py
timesketch_cli_client/commands/search.py
timesketch_cli_client/commands/search_test.py
timesketch_cli_client/commands/sigma.py
timesketch_cli_client/commands/sigma_test.py
timesketch_cli_client/commands/sketch.py
timesketch_cli_client/commands/sketch_test.py
timesketch_cli_client/commands/timelines.py
timesketch_cli_client/commands/timelines_test.py