Metadata-Version: 2.4
Name: timesketch-cli-client
Version: 20251112
Summary: Timesketch CLI client
Home-page: http://www.timesketch.org/
Maintainer: Timesketch development team
Maintainer-email: timesketch-dev@googlegroups.com
License: Apache License, Version 2.0
Classifier: Development Status :: 4 - Beta
Classifier: Environment :: Console
Classifier: Operating System :: OS Independent
Classifier: Programming Language :: Python
Requires-Dist: pandas
Requires-Dist: timesketch-import-client
Requires-Dist: timesketch-api-client
Requires-Dist: tabulate
Requires-Dist: click
Dynamic: classifier
Dynamic: home-page
Dynamic: license
Dynamic: maintainer
Dynamic: maintainer-email
Dynamic: requires-dist
Dynamic: summary
